montecarlosim/__init__.py
montecarlosim/exceptions.py
montecarlosim/functions.py
montecarlosim/montecarlo.py
montecarlosim-0.1.0.dist-info/LICENSE
montecarlosim-0.1.0.dist-info/WHEEL
montecarlosim-0.1.0.dist-info/entry_points.txt
montecarlosim-0.1.0.dist-info/METADATA
montecarlosim-0.1.0.dist-info/RECORD
