Metadata-Version: 2.1
Name: montecarlosim
Version: 0.1.0
Summary: MonteCarlo simulation library
License: MIT
Author: Valerio Farrotti
Author-email: valerio.farrotti@gmail.com
Maintainer: Valerio Farrotti
Maintainer-email: valerio.farrotti@gmail.com
Requires-Python: >=3.10.0,<4.0.0
Classifier: Development Status :: 2 - Pre-Alpha
Classifier: Intended Audience :: Developers
Classifier: Intended Audience :: Science/Research
Classifier: License :: OSI Approved :: MIT License
Classifier: Natural Language :: English
Classifier: Operating System :: OS Independent
Classifier: Programming Language :: Python :: 3
Classifier: Programming Language :: Python :: 3.10
Classifier: Programming Language :: Python :: 3.11
Classifier: Programming Language :: Python :: 3
Classifier: Topic :: Scientific/Engineering
Requires-Dist: matplotlib (>=3.6.0,<3.7.0)
Requires-Dist: numpy (>=1.24.0,<1.25.0)
